{"Grass":[{"GrassX":4,"GrassY":6},{"GrassX":2,"GrassY":3},{"GrassX":10,"GrassY":9},{"GrassX":3,"GrassY":2},{"GrassX":3,"GrassY":5},{"GrassX":15,"GrassY":9},{"GrassX":6,"GrassY":2},{"GrassX":13,"GrassY":5},{"GrassX":5,"GrassY":3},{"GrassX":8,"GrassY":0},{"GrassX":2,"GrassY":5},{"GrassX":7,"GrassY":4},{"GrassX":1,"GrassY":1},{"GrassX":11,"GrassY":8},{"GrassX":15,"GrassY":5},{"GrassX":15,"GrassY":4}],"Restricted":[{"BlockX":13,"BlockY":1},{"BlockX":3,"BlockY":5},{"BlockX":8,"BlockY":4},{"BlockX":14,"BlockY":5},{"BlockX":7,"BlockY":5},{"BlockX":14,"BlockY":3},{"BlockX":5,"BlockY":1},{"BlockX":1,"BlockY":6},{"BlockX":14,"BlockY":7},{"BlockX":3,"BlockY":4}]}