{"Grass":[{"GrassX":18,"GrassY":9},{"GrassX":13,"GrassY":3},{"GrassX":23,"GrassY":9},{"GrassX":16,"GrassY":1},{"GrassX":10,"GrassY":0},{"GrassX":12,"GrassY":2},{"GrassX":20,"GrassY":3},{"GrassX":11,"GrassY":1},{"GrassX":3,"GrassY":10},{"GrassX":6,"GrassY":3},{"GrassX":22,"GrassY":13},{"GrassX":3,"GrassY":8},{"GrassX":2,"GrassY":12},{"GrassX":6,"GrassY":5},{"GrassX":18,"GrassY":11},{"GrassX":17,"GrassY":7},{"GrassX":9,"GrassY":4},{"GrassX":17,"GrassY":4},{"GrassX":22,"GrassY":5},{"GrassX":10,"GrassY":4},{"GrassX":11,"GrassY":13},{"GrassX":12,"GrassY":3},{"GrassX":3,"GrassY":14},{"GrassX":9,"GrassY":3},{"GrassX":16,"GrassY":9},{"GrassX":12,"GrassY":7},{"GrassX":13,"GrassY":9},{"GrassX":3,"GrassY":9},{"GrassX":11,"GrassY":5},{"GrassX":0,"GrassY":3},{"GrassX":3,"GrassY":10},{"GrassX":17,"GrassY":8},{"GrassX":24,"GrassY":6},{"GrassX":21,"GrassY":13},{"GrassX":19,"GrassY":4},{"GrassX":4,"GrassY":3},{"GrassX":5,"GrassY":10},{"GrassX":12,"GrassY":5},{"GrassX":16,"GrassY":12},{"GrassX":15,"GrassY":4},{"GrassX":11,"GrassY":1},{"GrassX":20,"GrassY":0},{"GrassX":18,"GrassY":14},{"GrassX":15,"GrassY":3},{"GrassX":8,"GrassY":9},{"GrassX":10,"GrassY":7},{"GrassX":8,"GrassY":2},{"GrassX":0,"GrassY":5},{"GrassX":13,"GrassY":13},{"GrassX":5,"GrassY":5},{"GrassX":4,"GrassY":6},{"GrassX":14,"GrassY":6},{"GrassX":2,"GrassY":1},{"GrassX":19,"GrassY":11},{"GrassX":23,"GrassY":6},{"GrassX":1,"GrassY":6},{"GrassX":5,"GrassY":2},{"GrassX":1,"GrassY":4},{"GrassX":0,"GrassY":10},{"GrassX":11,"GrassY":6},{"GrassX":12,"GrassY":7},{"GrassX":12,"GrassY":12},{"GrassX":8,"GrassY":9},{"GrassX":3,"GrassY":1},{"GrassX":22,"GrassY":1},{"GrassX":9,"GrassY":3},{"GrassX":16,"GrassY":9},{"GrassX":12,"GrassY":11},{"GrassX":12,"GrassY":8},{"GrassX":14,"GrassY":8},{"GrassX":3,"GrassY":2}],"Restricted":[{"BlockX":13,"BlockY":13},{"BlockX":10,"BlockY":4},{"BlockX":21,"BlockY":0},{"BlockX":12,"BlockY":3},{"BlockX":16,"BlockY":14},{"BlockX":17,"BlockY":0},{"BlockX":2,"BlockY":10},{"BlockX":20,"BlockY":13},{"BlockX":4,"BlockY":4},{"BlockX":12,"BlockY":7},{"BlockX":4,"BlockY":13},{"BlockX":3,"BlockY":8},{"BlockX":17,"BlockY":13},{"BlockX":16,"BlockY":8},{"BlockX":20,"BlockY":10},{"BlockX":4,"BlockY":6}]}